goat_adapters/openai_agents_sdk/__init__.py
goat_adapters/openai_agents_sdk/adapter.py
goat_sdk_adapter_openai_agents_sdk-0.1.0.dist-info/METADATA
goat_sdk_adapter_openai_agents_sdk-0.1.0.dist-info/WHEEL
goat_sdk_adapter_openai_agents_sdk-0.1.0.dist-info/RECORD
