Metadata-Version: 2.1
Name: goat-sdk-adapter-openai-agents-sdk
Version: 0.1.0
Summary: Goat adapter for OpenAI Agents SDK
Home-page: https://ohmygoat.dev/
Keywords: goat,sdk,web3,agents,ai
Author: Andrea Villa
Author-email: andreakarimodm@gmail.com
Requires-Python: >=3.10,<4.0
Classifier: Programming Language :: Python :: 3
Classifier: Programming Language :: Python :: 3.10
Classifier: Programming Language :: Python :: 3.11
Classifier: Programming Language :: Python :: 3.12
Requires-Dist: goat-sdk (>=0.1.0,<0.2.0)
Requires-Dist: openai-agents (>=0.0.3,<0.0.4)
Project-URL: Bug Tracker, https://github.com/goat-sdk/goat/issues
Project-URL: Repository, https://github.com/goat-sdk/goat
